.coveragerc
AUTHORS
ChangeLog
LICENSE
README.rst
RELEASE.md
requirements.txt
setup.cfg
setup.py
containerctl/__init__.py
containerctl/command.py
containerctl/container.py
containerctl/errors.py
containerctl/tools.py
containerctl.egg-info/PKG-INFO
containerctl.egg-info/SOURCES.txt
containerctl.egg-info/dependency_links.txt
containerctl.egg-info/entry_points.txt
containerctl.egg-info/not-zip-safe
containerctl.egg-info/pbr.json
containerctl.egg-info/requires.txt
containerctl.egg-info/top_level.txt
containerctl/version/__init__.py
containerctl/version/base.py
containerctl/version/git.py
containerctl/version/script.py
tests/__init__.py
tests/base.py
tests/mocks.py
tests/test_container_build.py
tests/test_container_funcs.py
tests/test_container_push.py
tests/test_container_remove.py