Metadata-Version: 1.0
Name: containerctl
Version: 0.3.2
Summary: A tool for building and running Docker containers.
Home-page: UNKNOWN
Author: WiFast Engineering
Author-email: engineering@wifast.com
License: BSD-Modified
Platform: UNKNOWN
